{
  "required": true,
  "minVersion": "0.8",
  "package": "top.superxuqc.mcmod.mixin",
  "compatibilityLevel": "JAVA_21",
  "mixins": [
    "EnderPearItemMixin",
    "ToolItemMixin",
    "ServerPlayNetworkHandlerMixin",
    "SwordItemMixin",
    "ArrowEntityMixin",
    "ArrowItemMixin",
    "PersistentProjectileEntityMixin",
    "EntityMixin",
    "ActiveTargetGoalMixin",
    "ProjectileEntityMixin",
    "EnderPearlEntityMixin"
  ],
  "client": [

  ],
  "server": [],
  "injectors": {
    "defaultRequire": 1
  }
}